{
  "projects": [
    {
      "id": 2,
      "name": "Patrio Homa",
      "employer": "freelancing",
      "dateStartEnd": "2010 -2011",
      "description": "A blog-forum -news site done in Drupal 6. The articles are categorised. According to category are fit into specific panel. New article goes to top section of panel. Older articles go to read more section automatically.The site is also multilingual and includes the rather complicated Drupal tool panels ",
      "analyticalDescription": "http://sbaibos.com/patrio.html",
      "siteUrl": "http://www.sbaibos.com/patrio/",
      "photo": "http://sbaibos.com/img/patrio_main.jpg",
      "technologiesUsed": "Drupal 6, Drupal tools, CSS"
    },
    {
      "id": 3,
      "name": "mtsirigotis",
      "employer": "freelancing",
      "dateStartEnd": "august 2011 - sept 2011",
      "description": "A medical site for the Akeso clinic. Done in Drupal 6",
      "analyticalDescription": "",
      "siteUrl": "http://sbaibos.com/mtsirigotis/",
      "photo": "no photo",
      "technologiesUsed": "Drupal 6, Drupal tools, CSS, HTML"
    }
  ]
}
